{
  "8770ae56-7511-4d81-846c-fd3099a99a7d": {
    "user_id": "8770ae56-7511-4d81-846c-fd3099a99a7d",
    "bio": "\u2615 Kaffe elsker | Yogaentusiast",
    "hobbies": [
      "Yoga",
      "Kaffe",
      "L\u00e6sning"
    ],
    "interests": [
      "Yoga",
      "Kaffe",
      "L\u00e6sning"
    ],
    "profile_picture": "\u2728",
    "location": "K\u00f8benhavn",
    "looking_for": [
      "Venner",
      "F\u00e6llesskaber"
    ]
  },
  "812c064c-b54d-4bbe-abe1-27456cab1bf9": {
    "user_id": "812c064c-b54d-4bbe-abe1-27456cab1bf9",
    "bio": "\ud83d\udcf8 Fotograferer det hele | Gamer",
    "hobbies": [
      "Fotografi",
      "Vandring",
      "Gaming"
    ],
    "interests": [
      "Fotografi",
      "Vandring",
      "Gaming"
    ],
    "profile_picture": "\ud83c\udfae",
    "location": "K\u00f8benhavn",
    "looking_for": [
      "Venner",
      "F\u00e6llesskaber"
    ]
  },
  "655d275c-0e02-48df-bb7b-d0b9c4e1d71b": {
    "user_id": "655d275c-0e02-48df-bb7b-d0b9c4e1d71b",
    "bio": "\ud83c\udfa8 Artist & designer | Musikk-elsker",
    "hobbies": [
      "Kunst",
      "Design",
      "Musik"
    ],
    "interests": [
      "Kunst",
      "Design",
      "Musik"
    ],
    "profile_picture": "\ud83c\udfa8",
    "location": "K\u00f8benhavn",
    "looking_for": [
      "Venner",
      "F\u00e6llesskaber"
    ]
  },
  "602ab9e2-5b47-4a11-9fbe-b173963efdf7": {
    "user_id": "602ab9e2-5b47-4a11-9fbe-b173963efdf7",
    "bio": "\ud83d\udcaa Fitnessn\u00f8rd | Football fan",
    "hobbies": [
      "Tr\u00e6ning",
      "Football",
      "Sundhed"
    ],
    "interests": [
      "Tr\u00e6ning",
      "Football",
      "Sundhed"
    ],
    "profile_picture": "\u26bd",
    "location": "K\u00f8benhavn",
    "looking_for": [
      "Venner",
      "F\u00e6llesskaber"
    ]
  },
  "dbd20a1a-a1a5-4fc3-ab09-464f67fb3a03": {
    "user_id": "dbd20a1a-a1a5-4fc3-ab09-464f67fb3a03",
    "bio": "\ud83d\udc68\u200d\ud83c\udf73 Elsker at lave mad | Rejsejunkie",
    "hobbies": [
      "Madlavning",
      "Rejser",
      "Kaffe"
    ],
    "interests": [
      "Madlavning",
      "Rejser",
      "Kaffe"
    ],
    "profile_picture": "\ud83c\udf73",
    "location": "K\u00f8benhavn",
    "looking_for": [
      "Venner",
      "F\u00e6llesskaber"
    ]
  },
  "495fc84e-d55e-4bd1-9ee0-51a4651380eb": {
    "user_id": "495fc84e-d55e-4bd1-9ee0-51a4651380eb",
    "bio": "\ud83d\udcbb Developer | Tech geek",
    "hobbies": [
      "Programmering",
      "Tech",
      "Gaming"
    ],
    "interests": [
      "Programmering",
      "Tech",
      "Gaming"
    ],
    "profile_picture": "\ud83d\udc68\u200d\ud83d\udcbb",
    "location": "K\u00f8benhavn",
    "looking_for": [
      "Venner",
      "F\u00e6llesskaber"
    ]
  },
  "3b03cbb8-291f-4e93-8a08-04182b274a7e": {
    "user_id": "3b03cbb8-291f-4e93-8a08-04182b274a7e",
    "bio": "\ud83d\udc83 Danser | Film-elsker",
    "hobbies": [
      "Dans",
      "Musik",
      "Film"
    ],
    "interests": [
      "Dans",
      "Musik",
      "Film"
    ],
    "profile_picture": "\ud83c\udfac",
    "location": "K\u00f8benhavn",
    "looking_for": [
      "Venner",
      "F\u00e6llesskaber"
    ]
  },
  "1f23996f-aa79-4aeb-9ea5-30eff9725081": {
    "user_id": "1f23996f-aa79-4aeb-9ea5-30eff9725081",
    "bio": "\ud83c\udfb8 Musiker | Buskespiller",
    "hobbies": [
      "Musik",
      "Buskespil",
      "Rejser"
    ],
    "interests": [
      "Musik",
      "Buskespil",
      "Rejser"
    ],
    "profile_picture": "\ud83c\udfb5",
    "location": "K\u00f8benhavn",
    "looking_for": [
      "Venner",
      "F\u00e6llesskaber"
    ]
  },
  "41ea4600-bde7-413a-a106-e0e829af1470": {
    "user_id": "41ea4600-bde7-413a-a106-e0e829af1470",
    "bio": "",
    "hobbies": [],
    "interests": [],
    "profile_picture": "\ud83d\ude0a",
    "location": "",
    "looking_for": []
  },
  "90c6a6a2-b103-4e7a-bb48-1f31e939d4dc": {
    "user_id": "90c6a6a2-b103-4e7a-bb48-1f31e939d4dc",
    "bio": "\u2615 Altid klar p\u00e5 kaffe og en snak",
    "hobbies": [
      "Kaffe",
      "Gaming",
      "Fodbold"
    ],
    "interests": [
      "Kaffe",
      "Gaming",
      "Fodbold"
    ],
    "profile_picture": "\ud83d\ude04",
    "location": "K\u00f8benhavn",
    "looking_for": [
      "Venner",
      "F\u00e6llesskaber"
    ]
  },
  "f4920dc6-3694-47c9-b488-12cb6ca46b25": {
    "user_id": "f4920dc6-3694-47c9-b488-12cb6ca46b25",
    "bio": "\ud83c\udfb5 Elsker musik og gode vibes",
    "hobbies": [
      "Musik",
      "Tr\u00e6ning",
      "Rejser"
    ],
    "interests": [
      "Musik",
      "Tr\u00e6ning",
      "Rejser"
    ],
    "profile_picture": "\u2728",
    "location": "K\u00f8benhavn",
    "looking_for": [
      "Venner",
      "F\u00e6llesskaber"
    ]
  },
  "e655e088-b063-4384-bb77-097713e9159f": {
    "user_id": "e655e088-b063-4384-bb77-097713e9159f",
    "bio": "\ud83c\udfa8 Kreativ sj\u00e6l med grin p\u00e5",
    "hobbies": [
      "Design",
      "Film",
      "Madlavning"
    ],
    "interests": [
      "Design",
      "Film",
      "Madlavning"
    ],
    "profile_picture": "\ud83c\udf38",
    "location": "K\u00f8benhavn",
    "looking_for": [
      "Venner",
      "F\u00e6llesskaber"
    ]
  }
}